client_bank_exchange_1c/__init__.py
client_bank_exchange_1c/client_bank_exchange_1c.py
client_bank_exchange_1c/django_client_bank_exchange_1c.py
client_bank_exchange_1c-0.1.8.dist-info/DESCRIPTION.rst
client_bank_exchange_1c-0.1.8.dist-info/METADATA
client_bank_exchange_1c-0.1.8.dist-info/RECORD
client_bank_exchange_1c-0.1.8.dist-info/WHEEL
client_bank_exchange_1c-0.1.8.dist-info/metadata.json
client_bank_exchange_1c-0.1.8.dist-info/top_level.txt
