Metadata-Version: 2.0
Name: client-bank-exchange-1c
Version: 0.1.8
Summary: Handling of 1CClientBankExchange format
Home-page: https://github.com/kimaero/client_bank_exchange_1c
Author: Denis Kim
Author-email: denis@kim.aero
License: GNU General Public License v3
Keywords: client_bank_exchange_1c
Platform: UNKNOWN
Classifier: Development Status :: 2 - Pre-Alpha
Classifier: Intended Audience :: Developers
Classifier: License :: OSI Approved :: GNU General Public License v3 (GPLv3)
Classifier: Natural Language :: English
Classifier: Natural Language :: Russian
Classifier: Programming Language :: Python :: 3.6
